LICENSE
MANIFEST.in
README.md
requirements.txt
setup.py
squigualiser.egg-info/PKG-INFO
squigualiser.egg-info/SOURCES.txt
squigualiser.egg-info/dependency_links.txt
squigualiser.egg-info/entry_points.txt
squigualiser.egg-info/requires.txt
squigualiser.egg-info/top_level.txt
src/__init__.py
src/_version.py
src/bed_annotation.py
src/calculate_offsets.py
src/compare_alignment.py
src/f5c_eventalign_draw.py
src/f5c_resquiggle.py
src/metric.py
src/overlapped.py
src/plot.py
src/plot_model.py
src/plot_pileup.py
src/plot_tracks.py
src/plot_utils.py
src/readpaf_local.py
src/realign.py
src/reform.py
src/server.py
src/signal_chunk_plot.py
src/__pycache__/__init__.cpython-38.pyc
src/__pycache__/__init__.cpython-39.pyc
src/__pycache__/_version.cpython-38.pyc
src/__pycache__/_version.cpython-39.pyc
src/__pycache__/bed_annotation.cpython-38.pyc
src/__pycache__/bed_annotation.cpython-39.pyc
src/__pycache__/calculate_offsets.cpython-38.pyc
src/__pycache__/calculate_offsets.cpython-39.pyc
src/__pycache__/metric.cpython-38.pyc
src/__pycache__/plot.cpython-37.pyc
src/__pycache__/plot.cpython-38.pyc
src/__pycache__/plot.cpython-39.pyc
src/__pycache__/plot_pileup.cpython-37.pyc
src/__pycache__/plot_pileup.cpython-38.pyc
src/__pycache__/plot_pileup.cpython-39.pyc
src/__pycache__/plot_tracks.cpython-38.pyc
src/__pycache__/plot_tracks.cpython-39.pyc
src/__pycache__/plot_utils.cpython-38.pyc
src/__pycache__/plot_utils.cpython-39.pyc
src/__pycache__/realign.cpython-38.pyc
src/__pycache__/realign.cpython-39.pyc
src/__pycache__/reform.cpython-38.pyc
src/__pycache__/reform.cpython-39.pyc
src/server/home.html
src/server/script.js
src/server/style.css