Metadata-Version: 2.1
Name: squigualiser
Version: 0.6.3
Summary: Visualise ONT raw signals 
Home-page: https://github.com/hiruna72/squigualiser
Author: Hiruna Samarakoon
Author-email: h.samarakoon@garvan.org.au
Maintainer: Hiruna Samarakoon
Maintainer-email: h.samarakoon@garvan.org.au
License: MIT
Keywords: nanopore,slow5,signal
Classifier: Development Status :: 5 - Production/Stable
Classifier: Programming Language :: Python :: 3
Classifier: License :: OSI Approved :: MIT License
Classifier: Intended Audience :: Science/Research
Classifier: Topic :: Scientific/Engineering :: Bio-Informatics
Requires-Python: >=3.8
License-File: LICENSE
